{
  "team_id": 2,
  "team": "Telstar",
  "short_name": null,
  "matches": [
    {
      "date": "2026-03-22",
      "opponent": "PSV Eindhoven",
      "home_away": "H",
      "score": "3-1",
      "result": "W",
      "competition": "Eredivisie",
      "decided_in": "REGULAR",
      "source": "worldfootball.net"
    },
    {
      "date": "2026-03-14",
      "opponent": "Heerenveen",
      "home_away": "A",
      "score": "0-3",
      "result": "L",
      "competition": "Eredivisie",
      "decided_in": "REGULAR",
      "source": "worldfootball.net"
    },
    {
      "date": "2026-03-08",
      "opponent": "Fortuna Sittard",
      "home_away": "A",
      "score": "4-1",
      "result": "W",
      "competition": "Eredivisie",
      "decided_in": "REGULAR",
      "source": "worldfootball.net"
    },
    {
      "date": "2026-03-04",
      "opponent": "AZ Alkmaar",
      "home_away": "A",
      "score": "1-2",
      "result": "L",
      "competition": "KNVB Beker",
      "decided_in": "REGULAR",
      "source": "worldfootball.net"
    },
    {
      "date": "2026-02-27",
      "opponent": "NAC Breda",
      "home_away": "H",
      "score": "3-0",
      "result": "W",
      "competition": "Eredivisie",
      "decided_in": "REGULAR",
      "source": "worldfootball.net"
    },
    {
      "date": "2026-02-22",
      "opponent": "Feyenoord",
      "home_away": "A",
      "score": "1-2",
      "result": "L",
      "competition": "Eredivisie",
      "decided_in": "REGULAR",
      "source": "worldfootball.net"
    },
    {
      "date": "2026-02-15",
      "opponent": "FC Twente",
      "home_away": "H",
      "score": "1-1",
      "result": "D",
      "competition": "Eredivisie",
      "decided_in": "REGULAR",
      "source": "worldfootball.net"
    },
    {
      "date": "2026-02-09",
      "opponent": "Ajax",
      "home_away": "A",
      "score": "0-2",
      "result": "L",
      "competition": "KNVB Beker",
      "decided_in": "REGULAR",
      "source": "worldfootball.net"
    },
    {
      "date": "2026-02-08",
      "opponent": "Go Ahead Eagles",
      "home_away": "A",
      "score": "1-1",
      "result": "D",
      "competition": "Eredivisie",
      "decided_in": "REGULAR",
      "source": "worldfootball.net"
    },
    {
      "date": "2026-02-05",
      "opponent": "Go Ahead Eagles",
      "home_away": "H",
      "score": "2-1",
      "result": "W",
      "competition": "KNVB Beker",
      "decided_in": "REGULAR",
      "source": "worldfootball.net"
    },
    {
      "date": "2026-01-31",
      "opponent": "PEC Zwolle",
      "home_away": "A",
      "score": "1-4",
      "result": "L",
      "competition": "Eredivisie",
      "decided_in": "REGULAR",
      "source": "worldfootball.net"
    },
    {
      "date": "2026-01-25",
      "opponent": "AZ Alkmaar",
      "home_away": "H",
      "score": "0-1",
      "result": "L",
      "competition": "Eredivisie",
      "decided_in": "REGULAR",
      "source": "worldfootball.net"
    },
    {
      "date": "2026-01-17",
      "opponent": "Excelsior",
      "home_away": "A",
      "score": "2-2",
      "result": "D",
      "competition": "Eredivisie",
      "decided_in": "REGULAR",
      "source": "worldfootball.net"
    },
    {
      "date": "2026-01-14",
      "opponent": "Almere City FC",
      "home_away": "A",
      "score": "3-1",
      "result": "W",
      "competition": "KNVB Beker",
      "decided_in": "REGULAR",
      "source": "worldfootball.net"
    },
    {
      "date": "2026-01-11",
      "opponent": "Ajax",
      "home_away": "H",
      "score": "2-3",
      "result": "L",
      "competition": "Eredivisie",
      "decided_in": "REGULAR",
      "source": "worldfootball.net"
    },
    {
      "date": "2025-12-20",
      "opponent": "NAC Breda",
      "home_away": "A",
      "score": "1-0",
      "result": "W",
      "competition": "Eredivisie",
      "decided_in": "REGULAR",
      "source": "worldfootball.net"
    },
    {
      "date": "2025-12-16",
      "opponent": "HSV Hoek",
      "home_away": "A",
      "score": "4-1",
      "result": "W",
      "competition": "KNVB Beker",
      "decided_in": "REGULAR",
      "source": "worldfootball.net"
    },
    {
      "date": "2025-12-13",
      "opponent": "N.E.C.",
      "home_away": "H",
      "score": "2-2",
      "result": "D",
      "competition": "Eredivisie",
      "decided_in": "REGULAR",
      "source": "worldfootball.net"
    },
    {
      "date": "2025-12-06",
      "opponent": "Heracles Almelo",
      "home_away": "A",
      "score": "1-1",
      "result": "D",
      "competition": "Eredivisie",
      "decided_in": "REGULAR",
      "source": "worldfootball.net"
    },
    {
      "date": "2025-11-30",
      "opponent": "Feyenoord",
      "home_away": "H",
      "score": "1-2",
      "result": "L",
      "competition": "Eredivisie",
      "decided_in": "REGULAR",
      "source": "worldfootball.net"
    },
    {
      "date": "2025-11-23",
      "opponent": "FC Utrecht",
      "home_away": "H",
      "score": "1-1",
      "result": "D",
      "competition": "Eredivisie",
      "decided_in": "REGULAR",
      "source": "worldfootball.net"
    },
    {
      "date": "2025-11-07",
      "opponent": "FC Twente",
      "home_away": "A",
      "score": "0-0",
      "result": "D",
      "competition": "Eredivisie",
      "decided_in": "REGULAR",
      "source": "worldfootball.net"
    },
    {
      "date": "2025-11-01",
      "opponent": "Excelsior",
      "home_away": "H",
      "score": "2-2",
      "result": "D",
      "competition": "Eredivisie",
      "decided_in": "REGULAR",
      "source": "worldfootball.net"
    },
    {
      "date": "2025-10-29",
      "opponent": "FC Lisse",
      "home_away": "A",
      "score": "5-0",
      "result": "W",
      "competition": "KNVB Beker",
      "decided_in": "REGULAR",
      "source": "worldfootball.net"
    },
    {
      "date": "2025-10-25",
      "opponent": "Sp. Rotterdam",
      "home_away": "A",
      "score": "0-1",
      "result": "L",
      "competition": "Eredivisie",
      "decided_in": "REGULAR",
      "source": "worldfootball.net"
    },
    {
      "date": "2025-10-19",
      "opponent": "Heerenveen",
      "home_away": "H",
      "score": "2-3",
      "result": "L",
      "competition": "Eredivisie",
      "decided_in": "REGULAR",
      "source": "worldfootball.net"
    },
    {
      "date": "2025-10-07",
      "opponent": "TOP Oss",
      "home_away": "H",
      "score": "3-4",
      "result": "L",
      "competition": "KNVB Beker",
      "decided_in": "REGULAR",
      "source": "worldfootball.net"
    },
    {
      "date": "2025-10-05",
      "opponent": "AZ Alkmaar",
      "home_away": "A",
      "score": "1-2",
      "result": "L",
      "competition": "Eredivisie",
      "decided_in": "REGULAR",
      "source": "worldfootball.net"
    },
    {
      "date": "2025-09-28",
      "opponent": "Go Ahead Eagles",
      "home_away": "H",
      "score": "4-2",
      "result": "W",
      "competition": "Eredivisie",
      "decided_in": "REGULAR",
      "source": "worldfootball.net"
    },
    {
      "date": "2025-09-20",
      "opponent": "Groningen",
      "home_away": "A",
      "score": "0-2",
      "result": "L",
      "competition": "Eredivisie",
      "decided_in": "REGULAR",
      "source": "worldfootball.net"
    },
    {
      "date": "2025-09-14",
      "opponent": "Fortuna Sittard",
      "home_away": "H",
      "score": "1-3",
      "result": "L",
      "competition": "Eredivisie",
      "decided_in": "REGULAR",
      "source": "worldfootball.net"
    },
    {
      "date": "2025-08-30",
      "opponent": "PSV Eindhoven",
      "home_away": "A",
      "score": "2-0",
      "result": "W",
      "competition": "Eredivisie",
      "decided_in": "REGULAR",
      "source": "worldfootball.net"
    },
    {
      "date": "2025-08-23",
      "opponent": "FC Volendam",
      "home_away": "H",
      "score": "2-2",
      "result": "D",
      "competition": "Eredivisie",
      "decided_in": "REGULAR",
      "source": "worldfootball.net"
    },
    {
      "date": "2025-08-18",
      "opponent": "Sp. Rotterdam",
      "home_away": "A",
      "score": "2-4",
      "result": "L",
      "competition": "KNVB Beker",
      "decided_in": "REGULAR",
      "source": "worldfootball.net"
    },
    {
      "date": "2025-08-15",
      "opponent": "PEC Zwolle",
      "home_away": "H",
      "score": "0-2",
      "result": "L",
      "competition": "Eredivisie",
      "decided_in": "REGULAR",
      "source": "worldfootball.net"
    },
    {
      "date": "2025-08-10",
      "opponent": "Ajax",
      "home_away": "A",
      "score": "0-2",
      "result": "L",
      "competition": "Eredivisie",
      "decided_in": "REGULAR",
      "source": "worldfootball.net"
    },
    {
      "date": "2025-08-04",
      "opponent": "Al Shamal",
      "home_away": "H",
      "score": "2-1",
      "result": "W",
      "competition": "KNVB Beker",
      "decided_in": "REGULAR",
      "source": "worldfootball.net"
    },
    {
      "date": "2025-07-29",
      "opponent": "Sparta Rotterdam (J)",
      "home_away": "A",
      "score": "0-5",
      "result": "L",
      "competition": "KNVB Beker",
      "decided_in": "REGULAR",
      "source": "worldfootball.net"
    },
    {
      "date": "2025-07-22",
      "opponent": "Samsunspor",
      "home_away": "H",
      "score": "3-3",
      "result": "D",
      "competition": "KNVB Beker",
      "decided_in": "REGULAR",
      "source": "worldfootball.net"
    },
    {
      "date": "2025-07-19",
      "opponent": "SC Cambuur",
      "home_away": "A",
      "score": "2-0",
      "result": "W",
      "competition": "KNVB Beker",
      "decided_in": "REGULAR",
      "source": "worldfootball.net"
    },
    {
      "date": "2025-07-15",
      "opponent": "Rijnsburgse B.",
      "home_away": "A",
      "score": "2-0",
      "result": "W",
      "competition": "KNVB Beker",
      "decided_in": "REGULAR",
      "source": "worldfootball.net"
    },
    {
      "date": "2025-07-11",
      "opponent": "Heerenveen",
      "home_away": "A",
      "score": "1-1",
      "result": "D",
      "competition": "KNVB Beker",
      "decided_in": "REGULAR",
      "source": "worldfootball.net"
    },
    {
      "date": "2025-07-05",
      "opponent": "ADO '20",
      "home_away": "A",
      "score": "6-1",
      "result": "W",
      "competition": "KNVB Beker",
      "decided_in": "REGULAR",
      "source": "worldfootball.net"
    },
    {
      "date": "2025-06-01",
      "opponent": "Willem II",
      "home_away": "A",
      "score": "3-1",
      "result": "W",
      "competition": "Eredivisie",
      "decided_in": "REGULAR",
      "source": "worldfootball.net"
    },
    {
      "date": "2025-05-29",
      "opponent": "Willem II",
      "home_away": "H",
      "score": "2-2",
      "result": "D",
      "competition": "Eredivisie",
      "decided_in": "REGULAR",
      "source": "worldfootball.net"
    },
    {
      "date": "2025-05-23",
      "opponent": "FC Den Bosch",
      "home_away": "H",
      "score": "2-1",
      "result": "W",
      "competition": "Eredivisie",
      "decided_in": "EXTRA_TIME",
      "source": "worldfootball.net"
    },
    {
      "date": "2025-05-20",
      "opponent": "FC Den Bosch",
      "home_away": "A",
      "score": "0-0",
      "result": "D",
      "competition": "Eredivisie",
      "decided_in": "REGULAR",
      "source": "worldfootball.net"
    },
    {
      "date": "2025-05-17",
      "opponent": "ADO Den Haag",
      "home_away": "A",
      "score": "1-0",
      "result": "W",
      "competition": "Eredivisie",
      "decided_in": "REGULAR",
      "source": "worldfootball.net"
    },
    {
      "date": "2025-05-13",
      "opponent": "ADO Den Haag",
      "home_away": "H",
      "score": "2-0",
      "result": "W",
      "competition": "Eredivisie",
      "decided_in": "REGULAR",
      "source": "worldfootball.net"
    },
    {
      "date": "2025-05-09",
      "opponent": "FC Emmen",
      "home_away": "H",
      "score": "3-0",
      "result": "W",
      "competition": "Eerste Divisie",
      "decided_in": "REGULAR",
      "source": "worldfootball.net"
    },
    {
      "date": "2025-05-02",
      "opponent": "De Graafs.",
      "home_away": "A",
      "score": "1-2",
      "result": "L",
      "competition": "Eerste Divisie",
      "decided_in": "REGULAR",
      "source": "worldfootball.net"
    },
    {
      "date": "2025-04-25",
      "opponent": "TOP Oss",
      "home_away": "H",
      "score": "3-2",
      "result": "W",
      "competition": "Eerste Divisie",
      "decided_in": "REGULAR",
      "source": "worldfootball.net"
    },
    {
      "date": "2025-04-18",
      "opponent": "FC Eindhoven",
      "home_away": "A",
      "score": "4-0",
      "result": "W",
      "competition": "Eerste Divisie",
      "decided_in": "REGULAR",
      "source": "worldfootball.net"
    },
    {
      "date": "2025-04-15",
      "opponent": "Excelsior",
      "home_away": "A",
      "score": "4-1",
      "result": "W",
      "competition": "Eredivisie",
      "decided_in": "REGULAR",
      "source": "worldfootball.net"
    },
    {
      "date": "2025-04-11",
      "opponent": "ADO Den Haag",
      "home_away": "H",
      "score": "1-1",
      "result": "D",
      "competition": "Eerste Divisie",
      "decided_in": "REGULAR",
      "source": "worldfootball.net"
    },
    {
      "date": "2025-04-05",
      "opponent": "Helmond Sport",
      "home_away": "A",
      "score": "2-2",
      "result": "D",
      "competition": "Eerste Divisie",
      "decided_in": "REGULAR",
      "source": "worldfootball.net"
    },
    {
      "date": "2025-04-01",
      "opponent": "Sp. Rotterdam",
      "home_away": "A",
      "score": "0-3",
      "result": "L",
      "competition": "Eredivisie",
      "decided_in": "REGULAR",
      "source": "worldfootball.net"
    },
    {
      "date": "2025-03-28",
      "opponent": "Vitesse",
      "home_away": "H",
      "score": "1-0",
      "result": "W",
      "competition": "Eerste Divisie",
      "decided_in": "REGULAR",
      "source": "worldfootball.net"
    },
    {
      "date": "2025-03-14",
      "opponent": "Roda JC",
      "home_away": "H",
      "score": "3-1",
      "result": "W",
      "competition": "Eerste Divisie",
      "decided_in": "REGULAR",
      "source": "worldfootball.net"
    },
    {
      "date": "2025-03-11",
      "opponent": "FC Volendam",
      "home_away": "A",
      "score": "0-3",
      "result": "L",
      "competition": "Eerste Divisie",
      "decided_in": "REGULAR",
      "source": "worldfootball.net"
    },
    {
      "date": "2025-03-07",
      "opponent": "FC Dordrecht",
      "home_away": "H",
      "score": "5-0",
      "result": "W",
      "competition": "Eerste Divisie",
      "decided_in": "REGULAR",
      "source": "worldfootball.net"
    },
    {
      "date": "2025-03-03",
      "opponent": "AZ (J)",
      "home_away": "A",
      "score": "2-1",
      "result": "W",
      "competition": "Eerste Divisie",
      "decided_in": "REGULAR",
      "source": "worldfootball.net"
    },
    {
      "date": "2025-02-21",
      "opponent": "Excelsior",
      "home_away": "H",
      "score": "1-3",
      "result": "L",
      "competition": "Eerste Divisie",
      "decided_in": "REGULAR",
      "source": "worldfootball.net"
    },
    {
      "date": "2025-02-14",
      "opponent": "FC Den Bosch",
      "home_away": "A",
      "score": "1-0",
      "result": "W",
      "competition": "Eerste Divisie",
      "decided_in": "REGULAR",
      "source": "worldfootball.net"
    },
    {
      "date": "2025-02-09",
      "opponent": "FC Utrecht (J)",
      "home_away": "H",
      "score": "6-0",
      "result": "W",
      "competition": "Eerste Divisie",
      "decided_in": "REGULAR",
      "source": "worldfootball.net"
    },
    {
      "date": "2025-01-31",
      "opponent": "SC Cambuur",
      "home_away": "A",
      "score": "1-2",
      "result": "L",
      "competition": "Eerste Divisie",
      "decided_in": "REGULAR",
      "source": "worldfootball.net"
    },
    {
      "date": "2025-01-27",
      "opponent": "Willem II",
      "home_away": "A",
      "score": "1-2",
      "result": "L",
      "competition": "Eredivisie",
      "decided_in": "REGULAR",
      "source": "worldfootball.net"
    },
    {
      "date": "2025-01-25",
      "opponent": "Ajax (J)",
      "home_away": "H",
      "score": "3-0",
      "result": "W",
      "competition": "Eerste Divisie",
      "decided_in": "REGULAR",
      "source": "worldfootball.net"
    },
    {
      "date": "2025-01-17",
      "opponent": "VVV",
      "home_away": "A",
      "score": "0-1",
      "result": "L",
      "competition": "Eerste Divisie",
      "decided_in": "REGULAR",
      "source": "worldfootball.net"
    },
    {
      "date": "2025-01-14",
      "opponent": "Sp. Rotterdam",
      "home_away": "A",
      "score": "1-2",
      "result": "L",
      "competition": "Eredivisie",
      "decided_in": "REGULAR",
      "source": "worldfootball.net"
    },
    {
      "date": "2025-01-12",
      "opponent": "Jong PSV",
      "home_away": "H",
      "score": "1-0",
      "result": "W",
      "competition": "Eerste Divisie",
      "decided_in": "REGULAR",
      "source": "worldfootball.net"
    },
    {
      "date": "2025-01-07",
      "opponent": "Koninklijke HFC",
      "home_away": "H",
      "score": "4-1",
      "result": "W",
      "competition": "Eredivisie",
      "decided_in": "REGULAR",
      "source": "worldfootball.net"
    },
    {
      "date": "2025-01-04",
      "opponent": "ADO Den Haag",
      "home_away": "H",
      "score": "2-1",
      "result": "W",
      "competition": "Eredivisie",
      "decided_in": "REGULAR",
      "source": "worldfootball.net"
    },
    {
      "date": "2024-12-22",
      "opponent": "MVV",
      "home_away": "A",
      "score": "1-5",
      "result": "L",
      "competition": "Eerste Divisie",
      "decided_in": "REGULAR",
      "source": "worldfootball.net"
    },
    {
      "date": "2024-12-19",
      "opponent": "Ajax",
      "home_away": "A",
      "score": "0-2",
      "result": "L",
      "competition": "KNVB Beker",
      "decided_in": "REGULAR",
      "source": "worldfootball.net"
    },
    {
      "date": "2024-12-13",
      "opponent": "Helmond Sport",
      "home_away": "H",
      "score": "3-0",
      "result": "W",
      "competition": "Eerste Divisie",
      "decided_in": "REGULAR",
      "source": "worldfootball.net"
    },
    {
      "date": "2024-12-06",
      "opponent": "FC Dordrecht",
      "home_away": "A",
      "score": "2-3",
      "result": "L",
      "competition": "Eerste Divisie",
      "decided_in": "REGULAR",
      "source": "worldfootball.net"
    },
    {
      "date": "2024-11-29",
      "opponent": "SC Cambuur",
      "home_away": "H",
      "score": "2-2",
      "result": "D",
      "competition": "Eerste Divisie",
      "decided_in": "REGULAR",
      "source": "worldfootball.net"
    },
    {
      "date": "2024-11-22",
      "opponent": "Ajax (J)",
      "home_away": "A",
      "score": "0-3",
      "result": "L",
      "competition": "Eerste Divisie",
      "decided_in": "REGULAR",
      "source": "worldfootball.net"
    },
    {
      "date": "2024-11-15",
      "opponent": "VVV",
      "home_away": "H",
      "score": "4-0",
      "result": "W",
      "competition": "Eerste Divisie",
      "decided_in": "REGULAR",
      "source": "worldfootball.net"
    },
    {
      "date": "2024-11-09",
      "opponent": "Roda JC",
      "home_away": "A",
      "score": "0-1",
      "result": "L",
      "competition": "Eerste Divisie",
      "decided_in": "REGULAR",
      "source": "worldfootball.net"
    },
    {
      "date": "2024-11-03",
      "opponent": "FC Volendam",
      "home_away": "H",
      "score": "2-2",
      "result": "D",
      "competition": "Eerste Divisie",
      "decided_in": "REGULAR",
      "source": "worldfootball.net"
    },
    {
      "date": "2024-10-31",
      "opponent": "Helmond Sport",
      "home_away": "H",
      "score": "3-0",
      "result": "W",
      "competition": "KNVB Beker",
      "decided_in": "REGULAR",
      "source": "worldfootball.net"
    },
    {
      "date": "2024-10-27",
      "opponent": "FC Emmen",
      "home_away": "A",
      "score": "1-0",
      "result": "W",
      "competition": "Eerste Divisie",
      "decided_in": "REGULAR",
      "source": "worldfootball.net"
    },
    {
      "date": "2024-10-18",
      "opponent": "TOP Oss",
      "home_away": "A",
      "score": "1-1",
      "result": "D",
      "competition": "Eerste Divisie",
      "decided_in": "REGULAR",
      "source": "worldfootball.net"
    },
    {
      "date": "2024-10-12",
      "opponent": "De Graafs.",
      "home_away": "H",
      "score": "2-2",
      "result": "D",
      "competition": "Eerste Divisie",
      "decided_in": "REGULAR",
      "source": "worldfootball.net"
    },
    {
      "date": "2024-10-04",
      "opponent": "FC Utrecht (J)",
      "home_away": "A",
      "score": "1-1",
      "result": "D",
      "competition": "Eerste Divisie",
      "decided_in": "REGULAR",
      "source": "worldfootball.net"
    },
    {
      "date": "2024-09-28",
      "opponent": "FC Den Bosch",
      "home_away": "H",
      "score": "0-0",
      "result": "D",
      "competition": "Eerste Divisie",
      "decided_in": "REGULAR",
      "source": "worldfootball.net"
    },
    {
      "date": "2024-09-20",
      "opponent": "ADO Den Haag",
      "home_away": "A",
      "score": "1-1",
      "result": "D",
      "competition": "Eerste Divisie",
      "decided_in": "REGULAR",
      "source": "worldfootball.net"
    },
    {
      "date": "2024-09-13",
      "opponent": "Excelsior",
      "home_away": "A",
      "score": "2-3",
      "result": "L",
      "competition": "Eerste Divisie",
      "decided_in": "REGULAR",
      "source": "worldfootball.net"
    },
    {
      "date": "2024-09-08",
      "opponent": "MVV",
      "home_away": "H",
      "score": "4-0",
      "result": "W",
      "competition": "Eerste Divisie",
      "decided_in": "REGULAR",
      "source": "worldfootball.net"
    },
    {
      "date": "2024-08-30",
      "opponent": "AZ (J)",
      "home_away": "H",
      "score": "0-0",
      "result": "D",
      "competition": "Eerste Divisie",
      "decided_in": "REGULAR",
      "source": "worldfootball.net"
    },
    {
      "date": "2024-08-26",
      "opponent": "Jong PSV",
      "home_away": "A",
      "score": "2-0",
      "result": "W",
      "competition": "Eerste Divisie",
      "decided_in": "REGULAR",
      "source": "worldfootball.net"
    },
    {
      "date": "2024-08-16",
      "opponent": "FC Eindhoven",
      "home_away": "H",
      "score": "0-3",
      "result": "L",
      "competition": "Eerste Divisie",
      "decided_in": "REGULAR",
      "source": "worldfootball.net"
    },
    {
      "date": "2024-08-09",
      "opponent": "Vitesse",
      "home_away": "A",
      "score": "3-2",
      "result": "W",
      "competition": "Eerste Divisie",
      "decided_in": "REGULAR",
      "source": "worldfootball.net"
    },
    {
      "date": "2024-08-02",
      "opponent": "Umm-Salal",
      "home_away": "H",
      "score": "4-1",
      "result": "W",
      "competition": "Eredivisie",
      "decided_in": "REGULAR",
      "source": "worldfootball.net"
    },
    {
      "date": "2024-07-30",
      "opponent": "VV Noordwijk",
      "home_away": "H",
      "score": "5-3",
      "result": "W",
      "competition": "Eredivisie",
      "decided_in": "REGULAR",
      "source": "worldfootball.net"
    },
    {
      "date": "2024-07-13",
      "opponent": "Quick Boys",
      "home_away": "H",
      "score": "2-2",
      "result": "D",
      "competition": "Eredivisie",
      "decided_in": "REGULAR",
      "source": "worldfootball.net"
    },
    {
      "date": "2024-07-09",
      "opponent": "Ajax (J)",
      "home_away": "A",
      "score": "1-5",
      "result": "L",
      "competition": "Eredivisie",
      "decided_in": "REGULAR",
      "source": "worldfootball.net"
    },
    {
      "date": "2024-07-06",
      "opponent": "ADO '20",
      "home_away": "H",
      "score": "0-0",
      "result": "D",
      "competition": "Eredivisie",
      "decided_in": "REGULAR",
      "source": "worldfootball.net"
    },
    {
      "date": "2024-07-03",
      "opponent": "Go Ahead Eagles",
      "home_away": "A",
      "score": "0-3",
      "result": "L",
      "competition": "Eredivisie",
      "decided_in": "REGULAR",
      "source": "worldfootball.net"
    },
    {
      "date": "2024-05-10",
      "opponent": "Willem II",
      "home_away": "A",
      "score": "2-3",
      "result": "L",
      "competition": "Eerste Divisie",
      "decided_in": "REGULAR",
      "source": "worldfootball.net"
    },
    {
      "date": "2024-05-03",
      "opponent": "Groningen",
      "home_away": "H",
      "score": "1-1",
      "result": "D",
      "competition": "Eerste Divisie",
      "decided_in": "REGULAR",
      "source": "worldfootball.net"
    },
    {
      "date": "2024-04-28",
      "opponent": "FC Eindhoven",
      "home_away": "A",
      "score": "1-1",
      "result": "D",
      "competition": "Eerste Divisie",
      "decided_in": "REGULAR",
      "source": "worldfootball.net"
    },
    {
      "date": "2024-04-19",
      "opponent": "FC Emmen",
      "home_away": "H",
      "score": "2-3",
      "result": "L",
      "competition": "Eerste Divisie",
      "decided_in": "REGULAR",
      "source": "worldfootball.net"
    },
    {
      "date": "2024-04-12",
      "opponent": "De Graafs.",
      "home_away": "A",
      "score": "1-5",
      "result": "L",
      "competition": "Eerste Divisie",
      "decided_in": "REGULAR",
      "source": "worldfootball.net"
    },
    {
      "date": "2024-04-05",
      "opponent": "Jong PSV",
      "home_away": "H",
      "score": "3-1",
      "result": "W",
      "competition": "Eerste Divisie",
      "decided_in": "REGULAR",
      "source": "worldfootball.net"
    },
    {
      "date": "2024-03-29",
      "opponent": "FC Utrecht (J)",
      "home_away": "H",
      "score": "5-1",
      "result": "W",
      "competition": "Eerste Divisie",
      "decided_in": "REGULAR",
      "source": "worldfootball.net"
    },
    {
      "date": "2024-03-23",
      "opponent": "SC Cambuur",
      "home_away": "A",
      "score": "0-1",
      "result": "L",
      "competition": "Eerste Divisie",
      "decided_in": "REGULAR",
      "source": "worldfootball.net"
    },
    {
      "date": "2024-03-15",
      "opponent": "ADO Den Haag",
      "home_away": "H",
      "score": "3-1",
      "result": "W",
      "competition": "Eerste Divisie",
      "decided_in": "REGULAR",
      "source": "worldfootball.net"
    },
    {
      "date": "2024-03-08",
      "opponent": "FC Dordrecht",
      "home_away": "A",
      "score": "0-2",
      "result": "L",
      "competition": "Eerste Divisie",
      "decided_in": "REGULAR",
      "source": "worldfootball.net"
    },
    {
      "date": "2024-03-01",
      "opponent": "Roda JC",
      "home_away": "H",
      "score": "1-1",
      "result": "D",
      "competition": "Eerste Divisie",
      "decided_in": "REGULAR",
      "source": "worldfootball.net"
    },
    {
      "date": "2024-02-26",
      "opponent": "Ajax (J)",
      "home_away": "A",
      "score": "3-0",
      "result": "W",
      "competition": "Eerste Divisie",
      "decided_in": "REGULAR",
      "source": "worldfootball.net"
    },
    {
      "date": "2024-02-16",
      "opponent": "NAC Breda",
      "home_away": "H",
      "score": "1-1",
      "result": "D",
      "competition": "Eerste Divisie",
      "decided_in": "REGULAR",
      "source": "worldfootball.net"
    },
    {
      "date": "2024-02-09",
      "opponent": "Helmond Sport",
      "home_away": "H",
      "score": "3-2",
      "result": "W",
      "competition": "Eerste Divisie",
      "decided_in": "REGULAR",
      "source": "worldfootball.net"
    },
    {
      "date": "2024-02-02",
      "opponent": "MVV",
      "home_away": "A",
      "score": "1-6",
      "result": "L",
      "competition": "Eerste Divisie",
      "decided_in": "REGULAR",
      "source": "worldfootball.net"
    },
    {
      "date": "2024-01-26",
      "opponent": "FC Den Bosch",
      "home_away": "H",
      "score": "0-0",
      "result": "D",
      "competition": "Eerste Divisie",
      "decided_in": "REGULAR",
      "source": "worldfootball.net"
    },
    {
      "date": "2024-01-19",
      "opponent": "TOP Oss",
      "home_away": "A",
      "score": "0-1",
      "result": "L",
      "competition": "Eerste Divisie",
      "decided_in": "REGULAR",
      "source": "worldfootball.net"
    },
    {
      "date": "2024-01-12",
      "opponent": "AZ (J)",
      "home_away": "H",
      "score": "1-1",
      "result": "D",
      "competition": "Eerste Divisie",
      "decided_in": "REGULAR",
      "source": "worldfootball.net"
    },
    {
      "date": "2024-01-06",
      "opponent": "Koninklijke HFC",
      "home_away": "H",
      "score": "3-1",
      "result": "W",
      "competition": "KNVB Beker",
      "decided_in": "REGULAR",
      "source": "worldfootball.net"
    },
    {
      "date": "2023-12-22",
      "opponent": "VVV",
      "home_away": "A",
      "score": "1-2",
      "result": "L",
      "competition": "Eerste Divisie",
      "decided_in": "REGULAR",
      "source": "worldfootball.net"
    },
    {
      "date": "2023-12-15",
      "opponent": "FC Dordrecht",
      "home_away": "H",
      "score": "0-2",
      "result": "L",
      "competition": "Eerste Divisie",
      "decided_in": "REGULAR",
      "source": "worldfootball.net"
    },
    {
      "date": "2023-12-08",
      "opponent": "Groningen",
      "home_away": "A",
      "score": "0-2",
      "result": "L",
      "competition": "Eerste Divisie",
      "decided_in": "REGULAR",
      "source": "worldfootball.net"
    },
    {
      "date": "2023-12-04",
      "opponent": "FC Utrecht (J)",
      "home_away": "A",
      "score": "0-0",
      "result": "D",
      "competition": "Eerste Divisie",
      "decided_in": "REGULAR",
      "source": "worldfootball.net"
    },
    {
      "date": "2023-11-24",
      "opponent": "Willem II",
      "home_away": "H",
      "score": "1-5",
      "result": "L",
      "competition": "Eerste Divisie",
      "decided_in": "REGULAR",
      "source": "worldfootball.net"
    },
    {
      "date": "2023-11-17",
      "opponent": "FC Den Bosch",
      "home_away": "A",
      "score": "4-1",
      "result": "W",
      "competition": "Eerste Divisie",
      "decided_in": "REGULAR",
      "source": "worldfootball.net"
    },
    {
      "date": "2023-11-10",
      "opponent": "De Graafs.",
      "home_away": "H",
      "score": "1-2",
      "result": "L",
      "competition": "Eerste Divisie",
      "decided_in": "REGULAR",
      "source": "worldfootball.net"
    },
    {
      "date": "2023-11-03",
      "opponent": "Helmond Sport",
      "home_away": "A",
      "score": "0-1",
      "result": "L",
      "competition": "Eerste Divisie",
      "decided_in": "REGULAR",
      "source": "worldfootball.net"
    },
    {
      "date": "2023-10-31",
      "opponent": "GVVV",
      "home_away": "A",
      "score": "0-1",
      "result": "L",
      "competition": "KNVB Beker",
      "decided_in": "REGULAR",
      "source": "worldfootball.net"
    },
    {
      "date": "2023-10-27",
      "opponent": "TOP Oss",
      "home_away": "H",
      "score": "1-0",
      "result": "W",
      "competition": "Eerste Divisie",
      "decided_in": "REGULAR",
      "source": "worldfootball.net"
    },
    {
      "date": "2023-10-20",
      "opponent": "NAC Breda",
      "home_away": "A",
      "score": "1-3",
      "result": "L",
      "competition": "Eerste Divisie",
      "decided_in": "REGULAR",
      "source": "worldfootball.net"
    },
    {
      "date": "2023-10-14",
      "opponent": "MVV",
      "home_away": "H",
      "score": "2-1",
      "result": "W",
      "competition": "Eerste Divisie",
      "decided_in": "REGULAR",
      "source": "worldfootball.net"
    },
    {
      "date": "2023-10-06",
      "opponent": "FC Emmen",
      "home_away": "A",
      "score": "0-2",
      "result": "L",
      "competition": "Eerste Divisie",
      "decided_in": "REGULAR",
      "source": "worldfootball.net"
    },
    {
      "date": "2023-09-29",
      "opponent": "Ajax (J)",
      "home_away": "H",
      "score": "3-2",
      "result": "W",
      "competition": "Eerste Divisie",
      "decided_in": "REGULAR",
      "source": "worldfootball.net"
    },
    {
      "date": "2023-09-22",
      "opponent": "ADO Den Haag",
      "home_away": "A",
      "score": "1-1",
      "result": "D",
      "competition": "Eerste Divisie",
      "decided_in": "REGULAR",
      "source": "worldfootball.net"
    },
    {
      "date": "2023-09-15",
      "opponent": "Roda JC",
      "home_away": "A",
      "score": "0-3",
      "result": "L",
      "competition": "Eerste Divisie",
      "decided_in": "REGULAR",
      "source": "worldfootball.net"
    },
    {
      "date": "2023-09-09",
      "opponent": "VVV",
      "home_away": "H",
      "score": "1-2",
      "result": "L",
      "competition": "Eerste Divisie",
      "decided_in": "REGULAR",
      "source": "worldfootball.net"
    },
    {
      "date": "2023-09-01",
      "opponent": "FC Eindhoven",
      "home_away": "H",
      "score": "0-1",
      "result": "L",
      "competition": "Eerste Divisie",
      "decided_in": "REGULAR",
      "source": "worldfootball.net"
    },
    {
      "date": "2023-08-28",
      "opponent": "AZ (J)",
      "home_away": "A",
      "score": "1-3",
      "result": "L",
      "competition": "Eerste Divisie",
      "decided_in": "REGULAR",
      "source": "worldfootball.net"
    },
    {
      "date": "2023-08-18",
      "opponent": "SC Cambuur",
      "home_away": "H",
      "score": "2-3",
      "result": "L",
      "competition": "Eerste Divisie",
      "decided_in": "REGULAR",
      "source": "worldfootball.net"
    },
    {
      "date": "2023-08-14",
      "opponent": "Jong PSV",
      "home_away": "A",
      "score": "0-1",
      "result": "L",
      "competition": "Eerste Divisie",
      "decided_in": "REGULAR",
      "source": "worldfootball.net"
    },
    {
      "date": "2023-08-09",
      "opponent": "FC Utrecht (J)",
      "home_away": "A",
      "score": "2-0",
      "result": "W",
      "competition": "KNVB Beker",
      "decided_in": "REGULAR",
      "source": "worldfootball.net"
    },
    {
      "date": "2023-08-05",
      "opponent": "FC Den Bosch",
      "home_away": "H",
      "score": "4-0",
      "result": "W",
      "competition": "KNVB Beker",
      "decided_in": "REGULAR",
      "source": "worldfootball.net"
    },
    {
      "date": "2023-07-25",
      "opponent": "Rijnsburgse B.",
      "home_away": "H",
      "score": "1-0",
      "result": "W",
      "competition": "KNVB Beker",
      "decided_in": "REGULAR",
      "source": "worldfootball.net"
    },
    {
      "date": "2023-07-21",
      "opponent": "FC Eindhoven",
      "home_away": "H",
      "score": "3-1",
      "result": "W",
      "competition": "KNVB Beker",
      "decided_in": "REGULAR",
      "source": "worldfootball.net"
    },
    {
      "date": "2023-07-18",
      "opponent": "FC Lisse",
      "home_away": "A",
      "score": "6-1",
      "result": "W",
      "competition": "KNVB Beker",
      "decided_in": "REGULAR",
      "source": "worldfootball.net"
    },
    {
      "date": "2023-07-15",
      "opponent": "Exc. Maassluis",
      "home_away": "H",
      "score": "5-3",
      "result": "W",
      "competition": "KNVB Beker",
      "decided_in": "REGULAR",
      "source": "worldfootball.net"
    },
    {
      "date": "2023-07-11",
      "opponent": "ADO '20",
      "home_away": "H",
      "score": "2-1",
      "result": "W",
      "competition": "KNVB Beker",
      "decided_in": "REGULAR",
      "source": "worldfootball.net"
    },
    {
      "date": "2023-07-08",
      "opponent": "RKVV DEM",
      "home_away": "A",
      "score": "1-0",
      "result": "W",
      "competition": "KNVB Beker",
      "decided_in": "REGULAR",
      "source": "worldfootball.net"
    },
    {
      "date": "2023-07-04",
      "opponent": "HVV Hollandia",
      "home_away": "H",
      "score": "6-1",
      "result": "W",
      "competition": "KNVB Beker",
      "decided_in": "REGULAR",
      "source": "worldfootball.net"
    },
    {
      "date": "2023-07-01",
      "opponent": "VV IJmuiden",
      "home_away": "H",
      "score": "7-0",
      "result": "W",
      "competition": "KNVB Beker",
      "decided_in": "REGULAR",
      "source": "worldfootball.net"
    },
    {
      "date": "2023-05-19",
      "opponent": "NAC Breda",
      "home_away": "H",
      "score": "2-1",
      "result": "W",
      "competition": "Eerste Divisie",
      "decided_in": "REGULAR",
      "source": "worldfootball.net"
    },
    {
      "date": "2023-05-12",
      "opponent": "MVV",
      "home_away": "A",
      "score": "1-2",
      "result": "L",
      "competition": "Eerste Divisie",
      "decided_in": "REGULAR",
      "source": "worldfootball.net"
    },
    {
      "date": "2023-05-05",
      "opponent": "Willem II",
      "home_away": "H",
      "score": "0-0",
      "result": "D",
      "competition": "Eerste Divisie",
      "decided_in": "REGULAR",
      "source": "worldfootball.net"
    },
    {
      "date": "2023-04-28",
      "opponent": "FC Den Bosch",
      "home_away": "A",
      "score": "1-0",
      "result": "W",
      "competition": "Eerste Divisie",
      "decided_in": "REGULAR",
      "source": "worldfootball.net"
    },
    {
      "date": "2023-04-21",
      "opponent": "VVV",
      "home_away": "H",
      "score": "1-0",
      "result": "W",
      "competition": "Eerste Divisie",
      "decided_in": "REGULAR",
      "source": "worldfootball.net"
    },
    {
      "date": "2023-04-14",
      "opponent": "PEC Zwolle",
      "home_away": "A",
      "score": "0-2",
      "result": "L",
      "competition": "Eerste Divisie",
      "decided_in": "REGULAR",
      "source": "worldfootball.net"
    },
    {
      "date": "2023-04-07",
      "opponent": "Ajax (J)",
      "home_away": "H",
      "score": "2-3",
      "result": "L",
      "competition": "Eerste Divisie",
      "decided_in": "REGULAR",
      "source": "worldfootball.net"
    },
    {
      "date": "2023-03-31",
      "opponent": "ADO Den Haag",
      "home_away": "A",
      "score": "1-3",
      "result": "L",
      "competition": "Eerste Divisie",
      "decided_in": "REGULAR",
      "source": "worldfootball.net"
    },
    {
      "date": "2023-03-26",
      "opponent": "TOP Oss",
      "home_away": "H",
      "score": "1-0",
      "result": "W",
      "competition": "Eerste Divisie",
      "decided_in": "REGULAR",
      "source": "worldfootball.net"
    },
    {
      "date": "2023-03-17",
      "opponent": "Helmond Sport",
      "home_away": "A",
      "score": "2-2",
      "result": "D",
      "competition": "Eerste Divisie",
      "decided_in": "REGULAR",
      "source": "worldfootball.net"
    },
    {
      "date": "2023-03-10",
      "opponent": "Roda JC",
      "home_away": "A",
      "score": "2-1",
      "result": "W",
      "competition": "Eerste Divisie",
      "decided_in": "REGULAR",
      "source": "worldfootball.net"
    },
    {
      "date": "2023-03-03",
      "opponent": "FC Eindhoven",
      "home_away": "H",
      "score": "0-1",
      "result": "L",
      "competition": "Eerste Divisie",
      "decided_in": "REGULAR",
      "source": "worldfootball.net"
    },
    {
      "date": "2023-02-24",
      "opponent": "Heracles Almelo",
      "home_away": "A",
      "score": "0-7",
      "result": "L",
      "competition": "Eerste Divisie",
      "decided_in": "REGULAR",
      "source": "worldfootball.net"
    },
    {
      "date": "2023-02-17",
      "opponent": "Jong PSV",
      "home_away": "H",
      "score": "1-1",
      "result": "D",
      "competition": "Eerste Divisie",
      "decided_in": "REGULAR",
      "source": "worldfootball.net"
    },
    {
      "date": "2023-02-13",
      "opponent": "FC Utrecht (J)",
      "home_away": "A",
      "score": "1-0",
      "result": "W",
      "competition": "Eerste Divisie",
      "decided_in": "REGULAR",
      "source": "worldfootball.net"
    },
    {
      "date": "2023-02-03",
      "opponent": "De Graafs.",
      "home_away": "A",
      "score": "1-0",
      "result": "W",
      "competition": "Eerste Divisie",
      "decided_in": "REGULAR",
      "source": "worldfootball.net"
    },
    {
      "date": "2023-01-27",
      "opponent": "Almere City FC",
      "home_away": "H",
      "score": "0-1",
      "result": "L",
      "competition": "Eerste Divisie",
      "decided_in": "REGULAR",
      "source": "worldfootball.net"
    },
    {
      "date": "2023-01-24",
      "opponent": "MVV",
      "home_away": "H",
      "score": "5-3",
      "result": "W",
      "competition": "Eerste Divisie",
      "decided_in": "REGULAR",
      "source": "worldfootball.net"
    },
    {
      "date": "2023-01-21",
      "opponent": "FC Dordrecht",
      "home_away": "A",
      "score": "0-0",
      "result": "D",
      "competition": "Eerste Divisie",
      "decided_in": "REGULAR",
      "source": "worldfootball.net"
    },
    {
      "date": "2023-01-13",
      "opponent": "AZ (J)",
      "home_away": "H",
      "score": "1-0",
      "result": "W",
      "competition": "Eerste Divisie",
      "decided_in": "REGULAR",
      "source": "worldfootball.net"
    },
    {
      "date": "2023-01-10",
      "opponent": "FC Twente",
      "home_away": "A",
      "score": "1-3",
      "result": "L",
      "competition": "KNVB Beker",
      "decided_in": "REGULAR",
      "source": "worldfootball.net"
    },
    {
      "date": "2023-01-06",
      "opponent": "TOP Oss",
      "home_away": "A",
      "score": "1-2",
      "result": "L",
      "competition": "Eerste Divisie",
      "decided_in": "REGULAR",
      "source": "worldfootball.net"
    },
    {
      "date": "2022-12-30",
      "opponent": "Ajax",
      "home_away": "A",
      "score": "1-5",
      "result": "L",
      "competition": "KNVB Beker",
      "decided_in": "REGULAR",
      "source": "worldfootball.net"
    },
    {
      "date": "2022-12-11",
      "opponent": "FC Den Bosch",
      "home_away": "H",
      "score": "1-0",
      "result": "W",
      "competition": "Eerste Divisie",
      "decided_in": "REGULAR",
      "source": "worldfootball.net"
    },
    {
      "date": "2022-11-18",
      "opponent": "FC Eindhoven",
      "home_away": "A",
      "score": "0-3",
      "result": "L",
      "competition": "Eerste Divisie",
      "decided_in": "REGULAR",
      "source": "worldfootball.net"
    },
    {
      "date": "2022-11-11",
      "opponent": "ADO Den Haag",
      "home_away": "H",
      "score": "0-0",
      "result": "D",
      "competition": "Eerste Divisie",
      "decided_in": "REGULAR",
      "source": "worldfootball.net"
    },
    {
      "date": "2022-11-04",
      "opponent": "NAC Breda",
      "home_away": "A",
      "score": "1-1",
      "result": "D",
      "competition": "Eerste Divisie",
      "decided_in": "REGULAR",
      "source": "worldfootball.net"
    },
    {
      "date": "2022-10-28",
      "opponent": "FC Dordrecht",
      "home_away": "H",
      "score": "2-2",
      "result": "D",
      "competition": "Eerste Divisie",
      "decided_in": "REGULAR",
      "source": "worldfootball.net"
    },
    {
      "date": "2022-10-24",
      "opponent": "AZ (J)",
      "home_away": "A",
      "score": "0-0",
      "result": "D",
      "competition": "Eerste Divisie",
      "decided_in": "REGULAR",
      "source": "worldfootball.net"
    },
    {
      "date": "2022-10-18",
      "opponent": "Koninklijke HFC",
      "home_away": "A",
      "score": "1-0",
      "result": "W",
      "competition": "KNVB Beker",
      "decided_in": "REGULAR",
      "source": "worldfootball.net"
    },
    {
      "date": "2022-10-14",
      "opponent": "Roda JC",
      "home_away": "H",
      "score": "2-1",
      "result": "W",
      "competition": "Eerste Divisie",
      "decided_in": "REGULAR",
      "source": "worldfootball.net"
    },
    {
      "date": "2022-10-07",
      "opponent": "Jong PSV",
      "home_away": "A",
      "score": "2-0",
      "result": "W",
      "competition": "Eerste Divisie",
      "decided_in": "REGULAR",
      "source": "worldfootball.net"
    },
    {
      "date": "2022-09-30",
      "opponent": "FC Utrecht (J)",
      "home_away": "H",
      "score": "2-2",
      "result": "D",
      "competition": "Eerste Divisie",
      "decided_in": "REGULAR",
      "source": "worldfootball.net"
    },
    {
      "date": "2022-09-23",
      "opponent": "VVV",
      "home_away": "A",
      "score": "1-1",
      "result": "D",
      "competition": "Eerste Divisie",
      "decided_in": "REGULAR",
      "source": "worldfootball.net"
    },
    {
      "date": "2022-09-16",
      "opponent": "Heracles Almelo",
      "home_away": "H",
      "score": "0-3",
      "result": "L",
      "competition": "Eerste Divisie",
      "decided_in": "REGULAR",
      "source": "worldfootball.net"
    },
    {
      "date": "2022-09-09",
      "opponent": "Almere City FC",
      "home_away": "A",
      "score": "1-0",
      "result": "W",
      "competition": "Eerste Divisie",
      "decided_in": "REGULAR",
      "source": "worldfootball.net"
    },
    {
      "date": "2022-09-01",
      "opponent": "De Graafs.",
      "home_away": "H",
      "score": "0-1",
      "result": "L",
      "competition": "Eerste Divisie",
      "decided_in": "REGULAR",
      "source": "worldfootball.net"
    },
    {
      "date": "2022-08-26",
      "opponent": "Helmond Sport",
      "home_away": "H",
      "score": "2-1",
      "result": "W",
      "competition": "Eerste Divisie",
      "decided_in": "REGULAR",
      "source": "worldfootball.net"
    },
    {
      "date": "2022-08-19",
      "opponent": "Willem II",
      "home_away": "A",
      "score": "1-2",
      "result": "L",
      "competition": "Eerste Divisie",
      "decided_in": "REGULAR",
      "source": "worldfootball.net"
    },
    {
      "date": "2022-08-12",
      "opponent": "PEC Zwolle",
      "home_away": "H",
      "score": "0-5",
      "result": "L",
      "competition": "Eerste Divisie",
      "decided_in": "REGULAR",
      "source": "worldfootball.net"
    },
    {
      "date": "2022-08-08",
      "opponent": "Ajax (J)",
      "home_away": "A",
      "score": "1-1",
      "result": "D",
      "competition": "Eerste Divisie",
      "decided_in": "REGULAR",
      "source": "worldfootball.net"
    },
    {
      "date": "2022-08-02",
      "opponent": "HVV Hollandia",
      "home_away": "H",
      "score": "5-0",
      "result": "W",
      "competition": "KNVB Beker",
      "decided_in": "REGULAR",
      "source": "worldfootball.net"
    },
    {
      "date": "2022-07-26",
      "opponent": "IJsselmeerv.",
      "home_away": "H",
      "score": "1-0",
      "result": "W",
      "competition": "KNVB Beker",
      "decided_in": "REGULAR",
      "source": "worldfootball.net"
    },
    {
      "date": "2022-07-20",
      "opponent": "Spakenburg",
      "home_away": "A",
      "score": "2-2",
      "result": "D",
      "competition": "KNVB Beker",
      "decided_in": "REGULAR",
      "source": "worldfootball.net"
    },
    {
      "date": "2022-07-16",
      "opponent": "SC Cambuur",
      "home_away": "A",
      "score": "1-2",
      "result": "L",
      "competition": "KNVB Beker",
      "decided_in": "REGULAR",
      "source": "worldfootball.net"
    },
    {
      "date": "2022-07-12",
      "opponent": "Exc. Maassluis",
      "home_away": "A",
      "score": "0-0",
      "result": "D",
      "competition": "KNVB Beker",
      "decided_in": "REGULAR",
      "source": "worldfootball.net"
    },
    {
      "date": "2022-07-09",
      "opponent": "Willem II",
      "home_away": "A",
      "score": "0-2",
      "result": "L",
      "competition": "KNVB Beker",
      "decided_in": "REGULAR",
      "source": "worldfootball.net"
    },
    {
      "date": "2022-07-05",
      "opponent": "FC Lisse",
      "home_away": "H",
      "score": "2-0",
      "result": "W",
      "competition": "KNVB Beker",
      "decided_in": "REGULAR",
      "source": "worldfootball.net"
    },
    {
      "date": "2022-07-02",
      "opponent": "IJVV Stormvogels",
      "home_away": "H",
      "score": "3-2",
      "result": "W",
      "competition": "KNVB Beker",
      "decided_in": "REGULAR",
      "source": "worldfootball.net"
    },
    {
      "date": "2022-05-06",
      "opponent": "Roda JC",
      "home_away": "A",
      "score": "3-4",
      "result": "L",
      "competition": "Eerste Divisie",
      "decided_in": "REGULAR",
      "source": "worldfootball.net"
    },
    {
      "date": "2022-04-29",
      "opponent": "FC Utrecht (J)",
      "home_away": "H",
      "score": "1-3",
      "result": "L",
      "competition": "Eerste Divisie",
      "decided_in": "REGULAR",
      "source": "worldfootball.net"
    },
    {
      "date": "2022-04-22",
      "opponent": "FC Eindhoven",
      "home_away": "H",
      "score": "0-1",
      "result": "L",
      "competition": "Eerste Divisie",
      "decided_in": "REGULAR",
      "source": "worldfootball.net"
    },
    {
      "date": "2022-04-15",
      "opponent": "VVV",
      "home_away": "A",
      "score": "2-3",
      "result": "L",
      "competition": "Eerste Divisie",
      "decided_in": "REGULAR",
      "source": "worldfootball.net"
    },
    {
      "date": "2022-04-08",
      "opponent": "Excelsior",
      "home_away": "A",
      "score": "4-1",
      "result": "W",
      "competition": "Eerste Divisie",
      "decided_in": "REGULAR",
      "source": "worldfootball.net"
    },
    {
      "date": "2022-04-01",
      "opponent": "FC Den Bosch",
      "home_away": "H",
      "score": "1-2",
      "result": "L",
      "competition": "Eerste Divisie",
      "decided_in": "REGULAR",
      "source": "worldfootball.net"
    },
    {
      "date": "2022-03-27",
      "opponent": "FC Emmen",
      "home_away": "A",
      "score": "1-2",
      "result": "L",
      "competition": "Eerste Divisie",
      "decided_in": "REGULAR",
      "source": "worldfootball.net"
    },
    {
      "date": "2022-03-21",
      "opponent": "ADO Den Haag",
      "home_away": "A",
      "score": "1-2",
      "result": "L",
      "competition": "Eerste Divisie",
      "decided_in": "REGULAR",
      "source": "worldfootball.net"
    },
    {
      "date": "2022-03-18",
      "opponent": "FC Dordrecht",
      "home_away": "H",
      "score": "1-0",
      "result": "W",
      "competition": "Eerste Divisie",
      "decided_in": "REGULAR",
      "source": "worldfootball.net"
    },
    {
      "date": "2022-03-14",
      "opponent": "NAC Breda",
      "home_away": "H",
      "score": "1-4",
      "result": "L",
      "competition": "Eerste Divisie",
      "decided_in": "REGULAR",
      "source": "worldfootball.net"
    },
    {
      "date": "2022-03-07",
      "opponent": "AZ (J)",
      "home_away": "A",
      "score": "2-3",
      "result": "L",
      "competition": "Eerste Divisie",
      "decided_in": "REGULAR",
      "source": "worldfootball.net"
    },
    {
      "date": "2022-03-04",
      "opponent": "TOP Oss",
      "home_away": "H",
      "score": "2-2",
      "result": "D",
      "competition": "Eerste Divisie",
      "decided_in": "REGULAR",
      "source": "worldfootball.net"
    },
    {
      "date": "2022-02-11",
      "opponent": "Helmond Sport",
      "home_away": "A",
      "score": "2-2",
      "result": "D",
      "competition": "Eerste Divisie",
      "decided_in": "REGULAR",
      "source": "worldfootball.net"
    },
    {
      "date": "2022-02-04",
      "opponent": "De Graafs.",
      "home_away": "H",
      "score": "0-3",
      "result": "L",
      "competition": "Eerste Divisie",
      "decided_in": "REGULAR",
      "source": "worldfootball.net"
    },
    {
      "date": "2022-01-30",
      "opponent": "Almere City FC",
      "home_away": "A",
      "score": "0-0",
      "result": "D",
      "competition": "Eerste Divisie",
      "decided_in": "REGULAR",
      "source": "worldfootball.net"
    },
    {
      "date": "2022-01-23",
      "opponent": "Ajax (J)",
      "home_away": "H",
      "score": "1-0",
      "result": "W",
      "competition": "Eerste Divisie",
      "decided_in": "REGULAR",
      "source": "worldfootball.net"
    },
    {
      "date": "2022-01-20",
      "opponent": "PSV Eindhoven",
      "home_away": "A",
      "score": "1-2",
      "result": "L",
      "competition": "KNVB Beker",
      "decided_in": "REGULAR",
      "source": "worldfootball.net"
    },
    {
      "date": "2022-01-14",
      "opponent": "MVV",
      "home_away": "H",
      "score": "2-1",
      "result": "W",
      "competition": "Eerste Divisie",
      "decided_in": "REGULAR",
      "source": "worldfootball.net"
    },
    {
      "date": "2022-01-09",
      "opponent": "FC Volendam",
      "home_away": "A",
      "score": "1-2",
      "result": "L",
      "competition": "Eerste Divisie",
      "decided_in": "REGULAR",
      "source": "worldfootball.net"
    },
    {
      "date": "2021-12-17",
      "opponent": "Jong PSV",
      "home_away": "H",
      "score": "0-0",
      "result": "D",
      "competition": "Eerste Divisie",
      "decided_in": "REGULAR",
      "source": "worldfootball.net"
    },
    {
      "date": "2021-12-14",
      "opponent": "Spakenburg",
      "home_away": "H",
      "score": "5-3",
      "result": "W",
      "competition": "KNVB Beker",
      "decided_in": "EXTRA_TIME",
      "source": "worldfootball.net"
    },
    {
      "date": "2021-12-10",
      "opponent": "FC Eindhoven",
      "home_away": "A",
      "score": "1-1",
      "result": "D",
      "competition": "Eerste Divisie",
      "decided_in": "REGULAR",
      "source": "worldfootball.net"
    },
    {
      "date": "2021-12-03",
      "opponent": "VVV",
      "home_away": "H",
      "score": "1-3",
      "result": "L",
      "competition": "Eerste Divisie",
      "decided_in": "REGULAR",
      "source": "worldfootball.net"
    },
    {
      "date": "2021-11-26",
      "opponent": "TOP Oss",
      "home_away": "A",
      "score": "1-1",
      "result": "D",
      "competition": "Eerste Divisie",
      "decided_in": "REGULAR",
      "source": "worldfootball.net"
    },
    {
      "date": "2021-11-19",
      "opponent": "ADO Den Haag",
      "home_away": "H",
      "score": "0-2",
      "result": "L",
      "competition": "Eerste Divisie",
      "decided_in": "REGULAR",
      "source": "worldfootball.net"
    },
    {
      "date": "2021-11-14",
      "opponent": "De Graafs.",
      "home_away": "A",
      "score": "1-1",
      "result": "D",
      "competition": "Eerste Divisie",
      "decided_in": "REGULAR",
      "source": "worldfootball.net"
    },
    {
      "date": "2021-11-06",
      "opponent": "Excelsior",
      "home_away": "H",
      "score": "2-5",
      "result": "L",
      "competition": "Eerste Divisie",
      "decided_in": "REGULAR",
      "source": "worldfootball.net"
    },
    {
      "date": "2021-11-01",
      "opponent": "Ajax (J)",
      "home_away": "A",
      "score": "0-3",
      "result": "L",
      "competition": "Eerste Divisie",
      "decided_in": "REGULAR",
      "source": "worldfootball.net"
    },
    {
      "date": "2021-10-26",
      "opponent": "Kozakken Boys",
      "home_away": "A",
      "score": "2-1",
      "result": "W",
      "competition": "KNVB Beker",
      "decided_in": "EXTRA_TIME",
      "source": "worldfootball.net"
    },
    {
      "date": "2021-10-22",
      "opponent": "Helmond Sport",
      "home_away": "H",
      "score": "2-2",
      "result": "D",
      "competition": "Eerste Divisie",
      "decided_in": "REGULAR",
      "source": "worldfootball.net"
    },
    {
      "date": "2021-10-18",
      "opponent": "Jong PSV",
      "home_away": "A",
      "score": "3-2",
      "result": "W",
      "competition": "Eerste Divisie",
      "decided_in": "REGULAR",
      "source": "worldfootball.net"
    },
    {
      "date": "2021-10-15",
      "opponent": "FC Volendam",
      "home_away": "H",
      "score": "1-5",
      "result": "L",
      "competition": "Eerste Divisie",
      "decided_in": "REGULAR",
      "source": "worldfootball.net"
    },
    {
      "date": "2021-10-01",
      "opponent": "FC Den Bosch",
      "home_away": "A",
      "score": "1-0",
      "result": "W",
      "competition": "Eerste Divisie",
      "decided_in": "REGULAR",
      "source": "worldfootball.net"
    },
    {
      "date": "2021-09-24",
      "opponent": "AZ (J)",
      "home_away": "H",
      "score": "1-0",
      "result": "W",
      "competition": "Eerste Divisie",
      "decided_in": "REGULAR",
      "source": "worldfootball.net"
    },
    {
      "date": "2021-09-17",
      "opponent": "FC Dordrecht",
      "home_away": "A",
      "score": "1-0",
      "result": "W",
      "competition": "Eerste Divisie",
      "decided_in": "REGULAR",
      "source": "worldfootball.net"
    },
    {
      "date": "2021-09-10",
      "opponent": "Almere City FC",
      "home_away": "H",
      "score": "1-1",
      "result": "D",
      "competition": "Eerste Divisie",
      "decided_in": "REGULAR",
      "source": "worldfootball.net"
    },
    {
      "date": "2021-09-05",
      "opponent": "MVV",
      "home_away": "A",
      "score": "0-3",
      "result": "L",
      "competition": "Eerste Divisie",
      "decided_in": "REGULAR",
      "source": "worldfootball.net"
    },
    {
      "date": "2021-08-27",
      "opponent": "FC Utrecht (J)",
      "home_away": "A",
      "score": "0-3",
      "result": "L",
      "competition": "Eerste Divisie",
      "decided_in": "REGULAR",
      "source": "worldfootball.net"
    },
    {
      "date": "2021-08-20",
      "opponent": "Roda JC",
      "home_away": "H",
      "score": "3-4",
      "result": "L",
      "competition": "Eerste Divisie",
      "decided_in": "REGULAR",
      "source": "worldfootball.net"
    },
    {
      "date": "2021-08-13",
      "opponent": "NAC Breda",
      "home_away": "A",
      "score": "2-2",
      "result": "D",
      "competition": "Eerste Divisie",
      "decided_in": "REGULAR",
      "source": "worldfootball.net"
    },
    {
      "date": "2021-08-10",
      "opponent": "VVSB",
      "home_away": "A",
      "score": "2-0",
      "result": "W",
      "competition": "KNVB Beker",
      "decided_in": "REGULAR",
      "source": "worldfootball.net"
    },
    {
      "date": "2021-08-06",
      "opponent": "FC Emmen",
      "home_away": "H",
      "score": "1-1",
      "result": "D",
      "competition": "Eerste Divisie",
      "decided_in": "REGULAR",
      "source": "worldfootball.net"
    },
    {
      "date": "2021-07-27",
      "opponent": "Rijnsburgse B.",
      "home_away": "A",
      "score": "2-1",
      "result": "W",
      "competition": "KNVB Beker",
      "decided_in": "REGULAR",
      "source": "worldfootball.net"
    },
    {
      "date": "2021-07-24",
      "opponent": "De Graafs.",
      "home_away": "A",
      "score": "1-2",
      "result": "L",
      "competition": "KNVB Beker",
      "decided_in": "REGULAR",
      "source": "worldfootball.net"
    },
    {
      "date": "2021-07-20",
      "opponent": "Quick Boys",
      "home_away": "A",
      "score": "3-1",
      "result": "W",
      "competition": "KNVB Beker",
      "decided_in": "REGULAR",
      "source": "worldfootball.net"
    },
    {
      "date": "2021-07-17",
      "opponent": "Exc. Maassluis",
      "home_away": "A",
      "score": "1-2",
      "result": "L",
      "competition": "KNVB Beker",
      "decided_in": "REGULAR",
      "source": "worldfootball.net"
    },
    {
      "date": "2021-07-13",
      "opponent": "Sp. Rotterdam",
      "home_away": "H",
      "score": "0-0",
      "result": "D",
      "competition": "KNVB Beker",
      "decided_in": "REGULAR",
      "source": "worldfootball.net"
    },
    {
      "date": "2021-07-10",
      "opponent": "SC Cambuur",
      "home_away": "A",
      "score": "0-6",
      "result": "L",
      "competition": "KNVB Beker",
      "decided_in": "REGULAR",
      "source": "worldfootball.net"
    },
    {
      "date": "2021-05-12",
      "opponent": "Ajax (J)",
      "home_away": "H",
      "score": "1-2",
      "result": "L",
      "competition": "Eerste Divisie",
      "decided_in": "REGULAR",
      "source": "worldfootball.net"
    },
    {
      "date": "2021-05-07",
      "opponent": "FC Den Bosch",
      "home_away": "A",
      "score": "1-4",
      "result": "L",
      "competition": "Eerste Divisie",
      "decided_in": "REGULAR",
      "source": "worldfootball.net"
    },
    {
      "date": "2021-04-30",
      "opponent": "Jong PSV",
      "home_away": "H",
      "score": "2-2",
      "result": "D",
      "competition": "Eerste Divisie",
      "decided_in": "REGULAR",
      "source": "worldfootball.net"
    },
    {
      "date": "2021-04-25",
      "opponent": "FC Volendam",
      "home_away": "A",
      "score": "0-2",
      "result": "L",
      "competition": "Eerste Divisie",
      "decided_in": "REGULAR",
      "source": "worldfootball.net"
    },
    {
      "date": "2021-04-16",
      "opponent": "Excelsior",
      "home_away": "H",
      "score": "1-1",
      "result": "D",
      "competition": "Eerste Divisie",
      "decided_in": "REGULAR",
      "source": "worldfootball.net"
    },
    {
      "date": "2021-04-12",
      "opponent": "Almere City FC",
      "home_away": "A",
      "score": "1-1",
      "result": "D",
      "competition": "Eerste Divisie",
      "decided_in": "REGULAR",
      "source": "worldfootball.net"
    },
    {
      "date": "2021-04-05",
      "opponent": "N.E.C.",
      "home_away": "A",
      "score": "1-1",
      "result": "D",
      "competition": "Eerste Divisie",
      "decided_in": "REGULAR",
      "source": "worldfootball.net"
    },
    {
      "date": "2021-04-02",
      "opponent": "FC Utrecht (J)",
      "home_away": "H",
      "score": "2-3",
      "result": "L",
      "competition": "Eerste Divisie",
      "decided_in": "REGULAR",
      "source": "worldfootball.net"
    },
    {
      "date": "2021-03-29",
      "opponent": "FC Dordrecht",
      "home_away": "A",
      "score": "0-1",
      "result": "L",
      "competition": "Eerste Divisie",
      "decided_in": "REGULAR",
      "source": "worldfootball.net"
    },
    {
      "date": "2021-03-19",
      "opponent": "Roda JC",
      "home_away": "H",
      "score": "3-1",
      "result": "W",
      "competition": "Eerste Divisie",
      "decided_in": "REGULAR",
      "source": "worldfootball.net"
    },
    {
      "date": "2021-03-12",
      "opponent": "De Graafs.",
      "home_away": "H",
      "score": "1-2",
      "result": "L",
      "competition": "Eerste Divisie",
      "decided_in": "REGULAR",
      "source": "worldfootball.net"
    },
    {
      "date": "2021-03-05",
      "opponent": "SC Cambuur",
      "home_away": "A",
      "score": "1-3",
      "result": "L",
      "competition": "Eerste Divisie",
      "decided_in": "REGULAR",
      "source": "worldfootball.net"
    },
    {
      "date": "2021-02-26",
      "opponent": "MVV",
      "home_away": "A",
      "score": "0-2",
      "result": "L",
      "competition": "Eerste Divisie",
      "decided_in": "REGULAR",
      "source": "worldfootball.net"
    },
    {
      "date": "2021-02-19",
      "opponent": "FC Eindhoven",
      "home_away": "H",
      "score": "1-1",
      "result": "D",
      "competition": "Eerste Divisie",
      "decided_in": "REGULAR",
      "source": "worldfootball.net"
    },
    {
      "date": "2021-02-16",
      "opponent": "NAC Breda",
      "home_away": "H",
      "score": "1-2",
      "result": "L",
      "competition": "Eerste Divisie",
      "decided_in": "REGULAR",
      "source": "worldfootball.net"
    },
    {
      "date": "2021-02-13",
      "opponent": "Go Ahead Eagles",
      "home_away": "A",
      "score": "0-1",
      "result": "L",
      "competition": "Eerste Divisie",
      "decided_in": "REGULAR",
      "source": "worldfootball.net"
    },
    {
      "date": "2021-01-29",
      "opponent": "Helmond Sport",
      "home_away": "A",
      "score": "1-1",
      "result": "D",
      "competition": "Eerste Divisie",
      "decided_in": "REGULAR",
      "source": "worldfootball.net"
    },
    {
      "date": "2021-01-22",
      "opponent": "AZ (J)",
      "home_away": "H",
      "score": "2-2",
      "result": "D",
      "competition": "Eerste Divisie",
      "decided_in": "REGULAR",
      "source": "worldfootball.net"
    },
    {
      "date": "2021-01-16",
      "opponent": "TOP Oss",
      "home_away": "A",
      "score": "4-1",
      "result": "W",
      "competition": "Eerste Divisie",
      "decided_in": "REGULAR",
      "source": "worldfootball.net"
    },
    {
      "date": "2021-01-08",
      "opponent": "De Graafs.",
      "home_away": "A",
      "score": "0-2",
      "result": "L",
      "competition": "Eerste Divisie",
      "decided_in": "REGULAR",
      "source": "worldfootball.net"
    },
    {
      "date": "2021-01-03",
      "opponent": "N.E.C.",
      "home_away": "H",
      "score": "5-2",
      "result": "W",
      "competition": "Eerste Divisie",
      "decided_in": "REGULAR",
      "source": "worldfootball.net"
    },
    {
      "date": "2020-12-21",
      "opponent": "Ajax (J)",
      "home_away": "A",
      "score": "2-1",
      "result": "W",
      "competition": "Eerste Divisie",
      "decided_in": "REGULAR",
      "source": "worldfootball.net"
    },
    {
      "date": "2020-12-11",
      "opponent": "Almere City FC",
      "home_away": "H",
      "score": "2-3",
      "result": "L",
      "competition": "Eerste Divisie",
      "decided_in": "REGULAR",
      "source": "worldfootball.net"
    },
    {
      "date": "2020-12-04",
      "opponent": "SC Cambuur",
      "home_away": "H",
      "score": "1-2",
      "result": "L",
      "competition": "Eerste Divisie",
      "decided_in": "REGULAR",
      "source": "worldfootball.net"
    },
    {
      "date": "2020-11-30",
      "opponent": "FC Utrecht (J)",
      "home_away": "A",
      "score": "2-1",
      "result": "W",
      "competition": "Eerste Divisie",
      "decided_in": "REGULAR",
      "source": "worldfootball.net"
    },
    {
      "date": "2020-11-19",
      "opponent": "FC Dordrecht",
      "home_away": "H",
      "score": "2-0",
      "result": "W",
      "competition": "Eerste Divisie",
      "decided_in": "REGULAR",
      "source": "worldfootball.net"
    },
    {
      "date": "2020-11-14",
      "opponent": "NAC Breda",
      "home_away": "A",
      "score": "0-1",
      "result": "L",
      "competition": "Eerste Divisie",
      "decided_in": "REGULAR",
      "source": "worldfootball.net"
    },
    {
      "date": "2020-11-10",
      "opponent": "Go Ahead Eagles",
      "home_away": "H",
      "score": "1-2",
      "result": "L",
      "competition": "Eerste Divisie",
      "decided_in": "REGULAR",
      "source": "worldfootball.net"
    },
    {
      "date": "2020-11-02",
      "opponent": "AZ (J)",
      "home_away": "A",
      "score": "1-1",
      "result": "D",
      "competition": "Eerste Divisie",
      "decided_in": "REGULAR",
      "source": "worldfootball.net"
    },
    {
      "date": "2020-10-28",
      "opponent": "Heracles Almelo",
      "home_away": "A",
      "score": "0-3",
      "result": "L",
      "competition": "KNVB Beker",
      "decided_in": "REGULAR",
      "source": "worldfootball.net"
    },
    {
      "date": "2020-10-23",
      "opponent": "Helmond Sport",
      "home_away": "H",
      "score": "2-0",
      "result": "W",
      "competition": "Eerste Divisie",
      "decided_in": "REGULAR",
      "source": "worldfootball.net"
    },
    {
      "date": "2020-10-19",
      "opponent": "Roda JC",
      "home_away": "A",
      "score": "1-1",
      "result": "D",
      "competition": "Eerste Divisie",
      "decided_in": "REGULAR",
      "source": "worldfootball.net"
    },
    {
      "date": "2020-10-10",
      "opponent": "TOP Oss",
      "home_away": "H",
      "score": "1-1",
      "result": "D",
      "competition": "Eerste Divisie",
      "decided_in": "REGULAR",
      "source": "worldfootball.net"
    },
    {
      "date": "2020-10-02",
      "opponent": "Jong PSV",
      "home_away": "A",
      "score": "0-3",
      "result": "L",
      "competition": "Eerste Divisie",
      "decided_in": "REGULAR",
      "source": "worldfootball.net"
    },
    {
      "date": "2020-09-28",
      "opponent": "FC Den Bosch",
      "home_away": "H",
      "score": "6-1",
      "result": "W",
      "competition": "Eerste Divisie",
      "decided_in": "REGULAR",
      "source": "worldfootball.net"
    },
    {
      "date": "2020-09-22",
      "opponent": "Excelsior",
      "home_away": "A",
      "score": "2-1",
      "result": "W",
      "competition": "Eerste Divisie",
      "decided_in": "REGULAR",
      "source": "worldfootball.net"
    },
    {
      "date": "2020-09-15",
      "opponent": "ODIN '59",
      "home_away": "H",
      "score": "1-3",
      "result": "L",
      "competition": "KNVB Beker",
      "decided_in": "REGULAR",
      "source": "worldfootball.net"
    },
    {
      "date": "2020-09-13",
      "opponent": "MVV",
      "home_away": "H",
      "score": "1-2",
      "result": "L",
      "competition": "Eerste Divisie",
      "decided_in": "REGULAR",
      "source": "worldfootball.net"
    },
    {
      "date": "2020-09-08",
      "opponent": "AZ Alkmaar",
      "home_away": "A",
      "score": "1-2",
      "result": "L",
      "competition": "KNVB Beker",
      "decided_in": "REGULAR",
      "source": "worldfootball.net"
    },
    {
      "date": "2020-09-05",
      "opponent": "FC Eindhoven",
      "home_away": "A",
      "score": "3-2",
      "result": "W",
      "competition": "Eerste Divisie",
      "decided_in": "REGULAR",
      "source": "worldfootball.net"
    },
    {
      "date": "2020-08-30",
      "opponent": "FC Volendam",
      "home_away": "H",
      "score": "2-2",
      "result": "D",
      "competition": "Eerste Divisie",
      "decided_in": "REGULAR",
      "source": "worldfootball.net"
    },
    {
      "date": "2020-08-25",
      "opponent": "Heracles Almelo",
      "home_away": "A",
      "score": "0-4",
      "result": "L",
      "competition": "KNVB Beker",
      "decided_in": "REGULAR",
      "source": "worldfootball.net"
    },
    {
      "date": "2020-08-21",
      "opponent": "AZ Alkmaar",
      "home_away": "A",
      "score": "1-1",
      "result": "D",
      "competition": "KNVB Beker",
      "decided_in": "REGULAR",
      "source": "worldfootball.net"
    },
    {
      "date": "2020-08-18",
      "opponent": "Sp. Rotterdam",
      "home_away": "H",
      "score": "0-0",
      "result": "D",
      "competition": "KNVB Beker",
      "decided_in": "REGULAR",
      "source": "worldfootball.net"
    },
    {
      "date": "2020-08-15",
      "opponent": "FC Emmen",
      "home_away": "A",
      "score": "0-1",
      "result": "L",
      "competition": "KNVB Beker",
      "decided_in": "REGULAR",
      "source": "worldfootball.net"
    },
    {
      "date": "2020-08-11",
      "opponent": "HVV Hollandia",
      "home_away": "H",
      "score": "6-1",
      "result": "W",
      "competition": "KNVB Beker",
      "decided_in": "REGULAR",
      "source": "worldfootball.net"
    },
    {
      "date": "2020-08-08",
      "opponent": "Quick Boys",
      "home_away": "A",
      "score": "1-0",
      "result": "W",
      "competition": "KNVB Beker",
      "decided_in": "REGULAR",
      "source": "worldfootball.net"
    },
    {
      "date": "2020-08-05",
      "opponent": "Ajax (J)",
      "home_away": "A",
      "score": "0-2",
      "result": "L",
      "competition": "KNVB Beker",
      "decided_in": "REGULAR",
      "source": "worldfootball.net"
    },
    {
      "date": "2020-08-02",
      "opponent": "Go Ahead Eagles",
      "home_away": "A",
      "score": "0-0",
      "result": "D",
      "competition": "KNVB Beker",
      "decided_in": "REGULAR",
      "source": "worldfootball.net"
    },
    {
      "date": "2020-07-25",
      "opponent": "ADO '20",
      "home_away": "H",
      "score": "0-0",
      "result": "D",
      "competition": "KNVB Beker",
      "decided_in": "REGULAR",
      "source": "worldfootball.net"
    },
    {
      "date": "2020-03-06",
      "opponent": "Jong PSV",
      "home_away": "H",
      "score": "1-0",
      "result": "W",
      "competition": "Eerste Divisie",
      "decided_in": "REGULAR",
      "source": "worldfootball.net"
    },
    {
      "date": "2020-02-28",
      "opponent": "Ajax (J)",
      "home_away": "A",
      "score": "2-2",
      "result": "D",
      "competition": "Eerste Divisie",
      "decided_in": "REGULAR",
      "source": "worldfootball.net"
    },
    {
      "date": "2020-02-21",
      "opponent": "MVV",
      "home_away": "H",
      "score": "2-1",
      "result": "W",
      "competition": "Eerste Divisie",
      "decided_in": "REGULAR",
      "source": "worldfootball.net"
    },
    {
      "date": "2020-02-14",
      "opponent": "FC Volendam",
      "home_away": "A",
      "score": "1-1",
      "result": "D",
      "competition": "Eerste Divisie",
      "decided_in": "REGULAR",
      "source": "worldfootball.net"
    },
    {
      "date": "2020-02-07",
      "opponent": "N.E.C.",
      "home_away": "H",
      "score": "1-7",
      "result": "L",
      "competition": "Eerste Divisie",
      "decided_in": "REGULAR",
      "source": "worldfootball.net"
    },
    {
      "date": "2020-01-31",
      "opponent": "Almere City FC",
      "home_away": "A",
      "score": "2-4",
      "result": "L",
      "competition": "Eerste Divisie",
      "decided_in": "REGULAR",
      "source": "worldfootball.net"
    },
    {
      "date": "2020-01-24",
      "opponent": "TOP Oss",
      "home_away": "H",
      "score": "1-0",
      "result": "W",
      "competition": "Eerste Divisie",
      "decided_in": "REGULAR",
      "source": "worldfootball.net"
    },
    {
      "date": "2020-01-17",
      "opponent": "Excelsior",
      "home_away": "A",
      "score": "3-3",
      "result": "D",
      "competition": "Eerste Divisie",
      "decided_in": "REGULAR",
      "source": "worldfootball.net"
    },
    {
      "date": "2020-01-10",
      "opponent": "FC Eindhoven",
      "home_away": "H",
      "score": "2-0",
      "result": "W",
      "competition": "Eerste Divisie",
      "decided_in": "REGULAR",
      "source": "worldfootball.net"
    },
    {
      "date": "2019-12-22",
      "opponent": "AZ (J)",
      "home_away": "H",
      "score": "3-1",
      "result": "W",
      "competition": "Eerste Divisie",
      "decided_in": "REGULAR",
      "source": "worldfootball.net"
    },
    {
      "date": "2019-12-18",
      "opponent": "Ajax",
      "home_away": "H",
      "score": "3-4",
      "result": "L",
      "competition": "Eerste Divisie",
      "decided_in": "REGULAR",
      "source": "worldfootball.net"
    },
    {
      "date": "2019-12-13",
      "opponent": "De Graafs.",
      "home_away": "A",
      "score": "2-2",
      "result": "D",
      "competition": "Eerste Divisie",
      "decided_in": "REGULAR",
      "source": "worldfootball.net"
    },
    {
      "date": "2019-12-06",
      "opponent": "NAC Breda",
      "home_away": "H",
      "score": "1-1",
      "result": "D",
      "competition": "Eerste Divisie",
      "decided_in": "REGULAR",
      "source": "worldfootball.net"
    },
    {
      "date": "2019-11-29",
      "opponent": "Ajax (J)",
      "home_away": "H",
      "score": "2-3",
      "result": "L",
      "competition": "Eerste Divisie",
      "decided_in": "REGULAR",
      "source": "worldfootball.net"
    },
    {
      "date": "2019-11-22",
      "opponent": "FC Dordrecht",
      "home_away": "A",
      "score": "3-2",
      "result": "W",
      "competition": "Eerste Divisie",
      "decided_in": "REGULAR",
      "source": "worldfootball.net"
    },
    {
      "date": "2019-11-17",
      "opponent": "Go Ahead Eagles",
      "home_away": "H",
      "score": "0-2",
      "result": "L",
      "competition": "Eerste Divisie",
      "decided_in": "REGULAR",
      "source": "worldfootball.net"
    },
    {
      "date": "2019-11-08",
      "opponent": "Jong PSV",
      "home_away": "A",
      "score": "1-1",
      "result": "D",
      "competition": "Eerste Divisie",
      "decided_in": "REGULAR",
      "source": "worldfootball.net"
    },
    {
      "date": "2019-11-01",
      "opponent": "FC Utrecht (J)",
      "home_away": "H",
      "score": "2-0",
      "result": "W",
      "competition": "Eerste Divisie",
      "decided_in": "REGULAR",
      "source": "worldfootball.net"
    },
    {
      "date": "2019-10-29",
      "opponent": "Koninklijke HFC",
      "home_away": "A",
      "score": "2-1",
      "result": "W",
      "competition": "Eerste Divisie",
      "decided_in": "REGULAR",
      "source": "worldfootball.net"
    },
    {
      "date": "2019-10-25",
      "opponent": "Helmond Sport",
      "home_away": "A",
      "score": "4-1",
      "result": "W",
      "competition": "Eerste Divisie",
      "decided_in": "REGULAR",
      "source": "worldfootball.net"
    },
    {
      "date": "2019-10-18",
      "opponent": "Almere City FC",
      "home_away": "H",
      "score": "1-0",
      "result": "W",
      "competition": "Eerste Divisie",
      "decided_in": "REGULAR",
      "source": "worldfootball.net"
    },
    {
      "date": "2019-10-12",
      "opponent": "TOP Oss",
      "home_away": "A",
      "score": "2-2",
      "result": "D",
      "competition": "Eerste Divisie",
      "decided_in": "REGULAR",
      "source": "worldfootball.net"
    },
    {
      "date": "2019-10-04",
      "opponent": "Roda JC",
      "home_away": "H",
      "score": "1-2",
      "result": "L",
      "competition": "Eerste Divisie",
      "decided_in": "REGULAR",
      "source": "worldfootball.net"
    },
    {
      "date": "2019-09-27",
      "opponent": "FC Eindhoven",
      "home_away": "A",
      "score": "1-4",
      "result": "L",
      "competition": "Eerste Divisie",
      "decided_in": "REGULAR",
      "source": "worldfootball.net"
    },
    {
      "date": "2019-09-20",
      "opponent": "FC Volendam",
      "home_away": "H",
      "score": "1-2",
      "result": "L",
      "competition": "Eerste Divisie",
      "decided_in": "REGULAR",
      "source": "worldfootball.net"
    },
    {
      "date": "2019-09-13",
      "opponent": "MVV",
      "home_away": "A",
      "score": "2-1",
      "result": "W",
      "competition": "Eerste Divisie",
      "decided_in": "REGULAR",
      "source": "worldfootball.net"
    },
    {
      "date": "2019-09-07",
      "opponent": "SC Cambuur",
      "home_away": "H",
      "score": "0-2",
      "result": "L",
      "competition": "Eerste Divisie",
      "decided_in": "REGULAR",
      "source": "worldfootball.net"
    },
    {
      "date": "2019-08-30",
      "opponent": "N.E.C.",
      "home_away": "A",
      "score": "2-4",
      "result": "L",
      "competition": "Eerste Divisie",
      "decided_in": "REGULAR",
      "source": "worldfootball.net"
    },
    {
      "date": "2019-08-23",
      "opponent": "Excelsior",
      "home_away": "H",
      "score": "3-0",
      "result": "W",
      "competition": "Eerste Divisie",
      "decided_in": "REGULAR",
      "source": "worldfootball.net"
    },
    {
      "date": "2019-08-16",
      "opponent": "FC Den Bosch",
      "home_away": "A",
      "score": "1-0",
      "result": "W",
      "competition": "Eerste Divisie",
      "decided_in": "REGULAR",
      "source": "worldfootball.net"
    },
    {
      "date": "2019-08-12",
      "opponent": "AZ (J)",
      "home_away": "A",
      "score": "0-0",
      "result": "D",
      "competition": "Eerste Divisie",
      "decided_in": "REGULAR",
      "source": "worldfootball.net"
    },
    {
      "date": "2019-08-03",
      "opponent": "Rijnsburgse B.",
      "home_away": "A",
      "score": "1-0",
      "result": "W",
      "competition": "Eerste Divisie",
      "decided_in": "REGULAR",
      "source": "worldfootball.net"
    },
    {
      "date": "2019-07-30",
      "opponent": "VV Katwijk",
      "home_away": "H",
      "score": "3-0",
      "result": "W",
      "competition": "Eerste Divisie",
      "decided_in": "REGULAR",
      "source": "worldfootball.net"
    },
    {
      "date": "2019-07-27",
      "opponent": "Vitesse (J)",
      "home_away": "H",
      "score": "0-0",
      "result": "D",
      "competition": "Eerste Divisie",
      "decided_in": "REGULAR",
      "source": "worldfootball.net"
    },
    {
      "date": "2019-07-20",
      "opponent": "AZ (J)",
      "home_away": "H",
      "score": "3-2",
      "result": "W",
      "competition": "Eerste Divisie",
      "decided_in": "REGULAR",
      "source": "worldfootball.net"
    },
    {
      "date": "2019-07-16",
      "opponent": "Peter Barendse Academy",
      "home_away": "H",
      "score": "2-0",
      "result": "W",
      "competition": "Eerste Divisie",
      "decided_in": "REGULAR",
      "source": "worldfootball.net"
    },
    {
      "date": "2019-07-09",
      "opponent": "BVC Bloemendaal",
      "home_away": "H",
      "score": "5-0",
      "result": "W",
      "competition": "Eerste Divisie",
      "decided_in": "REGULAR",
      "source": "worldfootball.net"
    },
    {
      "date": "2019-07-06",
      "opponent": "VV IJmuiden",
      "home_away": "H",
      "score": "6-0",
      "result": "W",
      "competition": "Eerste Divisie",
      "decided_in": "REGULAR",
      "source": "worldfootball.net"
    }
  ],
  "streak": {
    "found": true,
    "start_index": 141,
    "end_index": 151,
    "length": 11
  }
}